currency_exchanger/__init__.py
currency_exchanger/lib.py
currencyexchanger-1.0.0.dist-info/LICENSE
currencyexchanger-1.0.0.dist-info/METADATA
currencyexchanger-1.0.0.dist-info/WHEEL
currencyexchanger-1.0.0.dist-info/top_level.txt
currencyexchanger-1.0.0.dist-info/RECORD
