Metadata-Version: 2.1
Name: currencyexchanger
Version: 1.0.0
Summary: This is a simple python package.
Home-page: https://github.com/surajkarki66/python-module
Author: Suraj Karki
Author-email: suraj.karki500@gmail.com
License: UNKNOWN
Platform: UNKNOWN
Classifier: Programming Language :: Python :: 3
Classifier: License :: OSI Approved :: MIT License
Classifier: Operating System :: OS Independent
Requires-Python: >=3.6
Requires-Dist: requests
Requires-Dist: cachetools
